Metadata-Version: 2.1
Name: dxfbox
Version: 0.1.0
Summary: simple python based dxf box generator
Home-page: https://github.com/multigcs/dxfbox/
Author: Oliver Dippel
Author-email: o.dippel@gmx.de
License: LICENSE
Platform: UNKNOWN
License-File: LICENSE
